{
    "__comment": "Made with TheDestruc7i0n's advancements generator: https://advancements.thedestruc7i0n.ca",
    "display": {
        "title": {
            "text": "Sonic goes *BUZZZ*",
            "color": "white",
            "bold": false
        },
        "description": {
            "text": "You made a sonic screwdriver",
            "color": "white"
        },
        "icon": {
            "item": "tardis:sonic_screwdriver"
        },
        "frame": "challenge",
        "show_toast": true,
        "announce_to_chat": true,
        "hidden": false
    },
    "criteria": {
        "get sonic 1": {
            "trigger": "minecraft:inventory_changed",
            "conditions": {
                "items": [
                    {
                        "item": "tardis:sonic_second",
                        "count": {
                            "min": 1,
                            "max": 1
                        }
                    }
                ]
            }
        },
        "get sonic 2": {
            "trigger": "minecraft:inventory_changed",
            "conditions": {
                "items": [
                    {
                        "item": "tardis:sonic_romana",
                        "count": {
                            "min": 1,
                            "max": 1
                        }
                    }
                ]
            }
        },
        "get sonic 3": {
            "trigger": "minecraft:inventory_changed",
            "conditions": {
                "items": [
                    {
                        "item": "tardis:sonic_war",
                        "count": {
                            "min": 1,
                            "max": 1
                        }
                    }
                ]
            }
        },
        "get sonic 4": {
            "trigger": "minecraft:inventory_changed",
            "conditions": {
                "items": [
                    {
                        "item": "tardis:sonic_lipstick",
                        "count": {
                            "min": 1,
                            "max": 1
                        }
                    }
                ]
            }
        },
        "get sonic 5": {
            "trigger": "minecraft:inventory_changed",
            "conditions": {
                "items": [
                    {
                        "item": "tardis:sonic_trowel",
                        "count": {
                            "min": 1,
                            "max": 1
                        }
                    }
                ]
            }
        },
        "get sonic 6": {
            "trigger": "minecraft:inventory_changed",
            "conditions": {
                "items": [
                    {
                        "item": "tardis:sonic_pen",
                        "count": {
                            "min": 1,
                            "max": 1
                        }
                    }
                ]
            }
        },
        "get sonic 7": {
            "trigger": "minecraft:inventory_changed",
            "conditions": {
                "items": [
                    {
                        "item": "tardis:sonic_seven",
                        "count": {
                            "min": 1,
                            "max": 1
                        }
                    }
                ]
            }
        },
        "get sonic 8": {
            "trigger": "minecraft:inventory_changed",
            "conditions": {
                "items": [
                    {
                        "item": "tardis:sonic_cane",
                        "count": {
                            "min": 1,
                            "max": 1
                        }
                    }
                ]
            }
        },
        "get sonic 9": {
            "trigger": "minecraft:inventory_changed",
            "conditions": {
                "items": [
                    {
                        "item": "tardis:sonic_screwdriver",
                        "count": {
                            "min": 1,
                            "max": 1
                        }
                    }
                ]
            }
        },
        "get sonic 10": {
            "trigger": "minecraft:inventory_changed",
            "conditions": {
                "items": [
                    {
                        "item": "tardis:sonic_screwdriver_13",
                        "count": {
                            "min": 1,
                            "max": 1
                        }
                    }
                ]
            }
        },
        "get sonic 11": {
            "trigger": "minecraft:inventory_changed",
            "conditions": {
                "items": [
                    {
                        "item": "tardis:sonic_10",
                        "count": {
                            "min": 1,
                            "max": 1
                        }
                    }
                ]
            }
        },
        "get sonic 12": {
            "trigger": "minecraft:inventory_changed",
            "conditions": {
                "items": [
                    {
                        "item": "tardis:sonic_seven",
                        "count": {
                            "min": 1,
                            "max": 1
                        }
                    }
                ]
            }
        },
        "get sonic 13": {
            "trigger": "minecraft:inventory_changed",
            "conditions": {
                "items": [
                    {
                        "item": "tardis:sonic_fifth"
                    }
                ]
            }
        },
        "get sonic 14": {
            "trigger": "minecraft:inventory_changed",
            "conditions": {
                "items": [
                    {
                        "item": "tardis:sonic_fourth",
                        "count": {
                            "min": 1,
                            "max": 1
                        }
                    }
                ]
            }
        },
        "get sonic 15": {
            "trigger": "minecraft:inventory_changed",
            "conditions": {
                "items": [
                    {
                        "item": "tardis:sonic_lance",
                        "count": {
                            "min": 1,
                            "max": 1
                        }
                    }
                ]
            }
        }
    },
    "requirements": [
        [
            "get sonic 2",
            "get sonic 3",
            "get sonic 4",
            "get sonic 5",
            "get sonic 6",
            "get sonic 7",
            "get sonic 8",
            "get sonic 9",
            "get sonic 10",
            "get sonic 11",
            "get sonic 12",
            "get sonic 13",
            "get sonic 14",
            "get sonic 15",
            "get sonic 1"
        ]
    ],
    "parent": "tardis:enter_tardis"
}